waeup.kofa-1.8.1-py2.7-nspkg.pth
waeup/.DS_Store
waeup/kofa/.DS_Store
waeup/kofa/__init__.py
waeup/kofa/app.py
waeup/kofa/async.pt
waeup/kofa/async.py
waeup/kofa/async_multidb.zcml
waeup/kofa/async_single.zcml
waeup/kofa/authentication.py
waeup/kofa/catalog.py
waeup/kofa/configuration.py
waeup/kofa/configure.zcml
waeup/kofa/datacenter.py
waeup/kofa/fees.py
waeup/kofa/frontpage.html
waeup/kofa/frontpage.rst
waeup/kofa/ftesting.zcml
waeup/kofa/imagestorage.py
waeup/kofa/interfaces.py
waeup/kofa/language.py
waeup/kofa/locales.zcml
waeup/kofa/mail.zcml
waeup/kofa/maintenance.py
waeup/kofa/meta.py
waeup/kofa/meta.zcml
waeup/kofa/objecthistory.py
waeup/kofa/permissions.py
waeup/kofa/refereeentries.py
waeup/kofa/reports.py
waeup/kofa/schoolgrades.py
waeup/kofa/scripts.py
waeup/kofa/smtp.py
waeup/kofa/sourcefactory.py
waeup/kofa/startup.py
waeup/kofa/testing.py
waeup/kofa/userscontainer.py
waeup/kofa/webservices.py
waeup/kofa/workflow.py
waeup/kofa/zcml.py
waeup/kofa/accesscodes/__init__.py
waeup/kofa/accesscodes/accesscode.py
waeup/kofa/accesscodes/batching.py
waeup/kofa/accesscodes/browser.py
waeup/kofa/accesscodes/catalog.py
waeup/kofa/accesscodes/export.py
waeup/kofa/accesscodes/interfaces.py
waeup/kofa/accesscodes/workflow.py
waeup/kofa/accesscodes/browser_templates/admintaskacbatches.pt
waeup/kofa/accesscodes/browser_templates/batchcontainer.pt
waeup/kofa/accesscodes/browser_templates/reimportbatchpage.pt
waeup/kofa/accesscodes/browser_templates/searchpage.pt
waeup/kofa/accesscodes/tests/__init__.py
waeup/kofa/accesscodes/tests/sample_ac_data.csv
waeup/kofa/accesscodes/tests/sample_ac_data_update.csv
waeup/kofa/accesscodes/tests/sample_batch_data.csv
waeup/kofa/accesscodes/tests/sample_import.csv
waeup/kofa/accesscodes/tests/test_accesscode.py
waeup/kofa/accesscodes/tests/test_batching.py
waeup/kofa/accesscodes/tests/test_catalog.py
waeup/kofa/accesscodes/tests/test_export.py
waeup/kofa/accesscodes/tests/test_workflow.py
waeup/kofa/applicants/.DS_Store
waeup.kofa-1.8.1.dist-info/LICENSE
waeup.kofa-1.8.1.dist-info/METADATA
waeup.kofa-1.8.1.dist-info/WHEEL
waeup.kofa-1.8.1.dist-info/entry_points.txt
waeup.kofa-1.8.1.dist-info/namespace_packages.txt
waeup.kofa-1.8.1.dist-info/top_level.txt
waeup.kofa-1.8.1.dist-info/RECORD
