Metadata-Version: 2.1
Name: waeup.kofa
Version: 1.8.1
Summary: A student online information and  registration portal
Home-page: http://www.waeup.org/
Author: The WAeUP team.
Author-email: de@waeup.org
License: GPL
Keywords: portal waeup kofa student university registration grok zope
Platform: UNKNOWN
Classifier: Development Status :: 4 - Beta
Classifier: Environment :: Web Environment
Classifier: Intended Audience :: Education
Classifier: License :: OSI Approved :: GNU General Public License (GPL)
Classifier: Programming Language :: Python
Classifier: Operating System :: POSIX
Classifier: Operating System :: POSIX :: Linux
Classifier: Programming Language :: Python :: 2
Classifier: Programming Language :: Python :: 2.7
Classifier: Programming Language :: Python :: 2 :: Only
Classifier: Programming Language :: Python :: Implementation :: CPython
Classifier: Framework :: Zope3
Classifier: Topic :: Education
Classifier: Topic :: Internet :: WWW/HTTP
Requires-Dist: setuptools
Requires-Dist: grok
Requires-Dist: grokcore.startup
Requires-Dist: grokui.admin
Requires-Dist: hurry.query
Requires-Dist: hurry.jquery
Requires-Dist: hurry.jqueryui
Requires-Dist: hurry.workflow (>=0.11)
Requires-Dist: docutils
Requires-Dist: zope.xmlpickle
Requires-Dist: hurry.file
Requires-Dist: hurry.zoperesource
Requires-Dist: zc.sourcefactory
Requires-Dist: megrok.layout
Requires-Dist: reportlab
Requires-Dist: Pillow
Requires-Dist: psutil
Requires-Dist: unicodecsv
Requires-Dist: zope.app.authentication
Requires-Dist: zope.app.file
Requires-Dist: zope.app.testing
Requires-Dist: zope.app.undo
Requires-Dist: zope.file
Requires-Dist: zope.interface (>=3.6.0)
Requires-Dist: zope.testbrowser
Requires-Dist: zope.i18n
Requires-Dist: zope.mimetype
Requires-Dist: zope.errorview
Requires-Dist: zope.schema (>=3.8.0)
Requires-Dist: zope.sendmail
Requires-Dist: ulif.loghandlers
Requires-Dist: zc.async[z3]
Requires-Dist: z3c.evalexception
Requires-Dist: PyPDF2
Provides-Extra: beaker
Requires-Dist: dolmen.beaker ; extra == 'beaker'
Provides-Extra: diazo
Requires-Dist: diazo ; extra == 'diazo'
Requires-Dist: webob ; extra == 'diazo'
Provides-Extra: docs
Requires-Dist: Sphinx ; extra == 'docs'
Requires-Dist: collective.recipe.sphinxbuilder ; extra == 'docs'
Requires-Dist: docutils ; extra == 'docs'
Requires-Dist: roman ; extra == 'docs'
Requires-Dist: repoze.sphinx.autointerface ; extra == 'docs'
Provides-Extra: test
Requires-Dist: z3c.testsetup ; extra == 'test'
Requires-Dist: zope.app.testing ; extra == 'test'
Requires-Dist: zope.testbrowser ; extra == 'test'
Requires-Dist: zope.testing ; extra == 'test'
Requires-Dist: unittest2 ; extra == 'test'
